jsrl_library_common/__init__.py
jsrl_library_common/constants/__init__.py
jsrl_library_common/constants/properties/config_properties_constants.py
jsrl_library_common/exceptions/__init__.py
jsrl_library_common/exceptions/properties/config_properties_exceptions.py
jsrl_library_common/utils/__init__.py
jsrl_library_common/utils/data/__init__.py
jsrl_library_common/utils/data/files.py
jsrl_library_common/utils/data/token.py
jsrl_library_common/utils/decorators/__init__.py
jsrl_library_common/utils/decorators/enum_extension.py
jsrl_library_common/utils/decorators/inject_parameters.py
jsrl_library_common/utils/properties/config_properties.py
jsrl_library_common-0.0.1.dist-info/licenses/LICENSE
jsrl_library_common-0.0.1.dist-info/METADATA
jsrl_library_common-0.0.1.dist-info/WHEEL
jsrl_library_common-0.0.1.dist-info/top_level.txt
jsrl_library_common-0.0.1.dist-info/RECORD
